<?xml version="1.0" encoding="UTF-8"?>
<message:AIXMBasicMessage xmlns:adr="http://www.aixm.aero/schema/5.1.1/extensions/EUR/ADR"
                          xmlns:aixm="http://www.aixm.aero/schema/5.1.1"
                          xmlns:gco="http://www.isotc211.org/2005/gco"
                          xmlns:gmd="http://www.isotc211.org/2005/gmd"
                          xmlns:gml="http://www.opengis.net/gml/3.2"
                          xmlns:gsr="http://www.isotc211.org/2005/gsr"
                          xmlns:gss="http://www.isotc211.org/2005/gss"
                          xmlns:gts="http://www.isotc211.org/2005/gts"
                          xmlns:message="http://www.aixm.aero/schema/5.1.1/message"
                          xmlns:xlink="http://www.w3.org/1999/xlink"
                          xmlns:xsd="http://www.w3.org/2001/XMLSchema"
                          xmlns:xsi="http://www.w3.org/2001/XMLSchema-instance"
                          xsi:schemaLocation="http://www.aixm.aero/schema/5.1.1/message http://www.aixm.aero/schema/5.1.1/message/AIXM_BasicMessage.xsd"
                          gml:id="M00001">
  <message:hasMember>
<aixm:AirportHeliport gml:id="uuid.089611fb-223c-40cf-8b77-103fe4132517">
  <gml:identifier codeSpace="urn:uuid:">089611fb-223c-40cf-8b77-103fe4132517</gml:identifier>
  <gml:boundedBy xsi:nil="true"/>
  <aixm:timeSlice>
    <aixm:AirportHeliportTimeSlice gml:id="uuid.a2fffa63-64a5-4b04-afab-796aeecba7d1">
      <gml:validTime>
        <gml:TimePeriod gml:id="uuid.22d3aca5-6d46-46ba-b135-32ceff071a48">
          <gml:beginPosition>2011-12-15T00:00:00Z</gml:beginPosition>
          <gml:endPosition indeterminatePosition="unknown"/>
        </gml:TimePeriod>
      </gml:validTime>
      <aixm:interpretation>BASELINE</aixm:interpretation>
      <aixm:sequenceNumber>1</aixm:sequenceNumber>
      <aixm:correctionNumber>0</aixm:correctionNumber>
      <aixm:featureLifetime>
        <gml:TimePeriod gml:id="uuid.42b1f35d-9909-49ec-9819-2c964ac82481">
          <gml:beginPosition>2010-08-26T00:00:00Z</gml:beginPosition>
          <gml:endPosition indeterminatePosition="unknown"/>
        </gml:TimePeriod>
      </aixm:featureLifetime>
      <aixm:designator>LRBG</aixm:designator>
      <aixm:name>GHIMBAV / IAR BRASOV</aixm:name>
      <aixm:locationIndicatorICAO>LRBG</aixm:locationIndicatorICAO>
      <aixm:type>HP</aixm:type>
      <aixm:fieldElevation uom="FT">1744</aixm:fieldElevation>
      <aixm:magneticVariation>4</aixm:magneticVariation>
      <aixm:dateMagneticVariation>2010</aixm:dateMagneticVariation>
      <aixm:magneticVariationChange>0.2</aixm:magneticVariationChange>
      <aixm:referenceTemperature uom="C">7.5</aixm:referenceTemperature>
      <!-- ERROR: Found AirportHeliportTimeSlice with Note and propertyName referring to non-existing feature property. Existing properties are ('designator', 'name', 'locationIndicatorICAO', 'designatorIATA', 'type', 'certifiedICAO', 'privateUse', 'controlType', 'fieldElevation', 'fieldElevationAccuracy', 'verticalDatum', 'magneticVariation', 'magneticVariationAccuracy', 'dateMagneticVariation', 'magneticVariationChange', 'referenceTemperature', 'altimeterCheckLocation', 'secondaryPowerSupply', 'windDirectionIndicator', 'landingDirectionIndicator', 'transitionAltitude', 'transitionLevel', 'lowestTemperature', 'abandoned', 'certificationDate', 'certificationExpirationDate', 'contaminant', 'servedCity', 'responsibleOrganisation', 'aRP', 'aviationBoundary', 'altimeterSource', 'contact', 'availability') -->
      <aixm:localType>TRANSITION AREA</aixm:localType>
      <aixm:servedCity>
        <aixm:City gml:id="uuid.9b7e62d2-8202-4653-b116-b483eb49a3ea">
          <aixm:name>GHIMBAV</aixm:name>
        </aixm:City>
      </aixm:servedCity>
      <aixm:responsibleOrganisation>
        <aixm:AirportHeliportResponsibilityOrganisation gml:id="uuid.a2548946-d6c1-4e14-b919-40b8fdf16785">
          <aixm:theOrganisationAuthority xlink:type="simple" xlink:href="urn:uuid:09424934-7dd9-0ae9-e053-0b751dc2b779"/>
        </aixm:AirportHeliportResponsibilityOrganisation>
      </aixm:responsibleOrganisation>
      <aixm:ARP>
        <aixm:ElevatedPoint xmlns="http://www.aixm.aero/schema/5.1.1/message"  xmlns:gmd="http://www.isotc211.org/2005/gmd" xmlns:gco="http://www.isotc211.org/2005/gco"  xmlns:xlink="http://www.w3.org/1999/xlink" xmlns:gml="http://www.opengis.net/gml/3.2"  xmlns:gts="http://www.isotc211.org/2005/gts" xmlns:aixm="http://www.aixm.aero/schema/5.1.1" srsName="urn:ogc:def:crs:EPSG::4326" gml:id="uuid.20bfd1c1-4bbd-4fad-8109-386f55382b6d">
          <gml:pos>45.69583 25.53389</gml:pos>
          <aixm:geoidUndulation uom="FT">126</aixm:geoidUndulation>
        </aixm:ElevatedPoint>
      </aixm:ARP>
      <aixm:contact>
        <aixm:ContactInformation gml:id="uuid.7a1ae1fa-0a56-4a6b-aa43-da385024f5c8">
          <aixm:phoneFax>
            <aixm:TelephoneContact gml:id="uuid.c3298cc7-881e-4b4a-be44-c8a0d0c70e51">
              <aixm:voice>+40-268-475107</aixm:voice>
            </aixm:TelephoneContact>
          </aixm:phoneFax>
        </aixm:ContactInformation>
      </aixm:contact>
      <aixm:contact>
        <aixm:ContactInformation gml:id="uuid.20e06750-496d-48d4-a725-106858702b8d">
          <aixm:phoneFax>
            <aixm:TelephoneContact gml:id="uuid.d33953ee-c572-4363-b118-f96a2d0b0dd6">
              <aixm:facsimile>+40-268-476981</aixm:facsimile>
            </aixm:TelephoneContact>
          </aixm:phoneFax>
        </aixm:ContactInformation>
      </aixm:contact>
      <aixm:contact>
        <aixm:ContactInformation gml:id="uuid.248655ea-5ac9-4f15-a6d0-93a22a03a322">
          <aixm:networkNode>
            <aixm:OnlineContact gml:id="uuid.99284cb0-7226-49c2-be32-48d70f7abf77">
              <aixm:network>INTERNET</aixm:network>
              <aixm:eMail>heliport@iar.ro</aixm:eMail>
            </aixm:OnlineContact>
          </aixm:networkNode>
        </aixm:ContactInformation>
      </aixm:contact>
      <aixm:contact>
        <aixm:ContactInformation gml:id="uuid.e1a83f91-466b-4f5b-9e9f-861b2590cf54">
          <aixm:networkNode>
            <aixm:OnlineContact gml:id="uuid.e3e4c8f5-7986-4237-bec0-f8c8360d0797">
              <aixm:network>INTERNET</aixm:network>
              <aixm:linkage>www.iar.ro</aixm:linkage>
            </aixm:OnlineContact>
          </aixm:networkNode>
        </aixm:ContactInformation>
      </aixm:contact>
      <aixm:contact>
        <aixm:ContactInformation gml:id="uuid.56c09eeb-5f86-420c-872c-e61cf25d12e6">
          <aixm:address>
            <aixm:PostalAddress gml:id="uuid.eec99d63-d6b4-42fb-8851-69f3f7ac7318">
              <aixm:deliveryPoint>SC IAR SA Ghimbav, str. Aeroportului Nr. 1, jud. Brasov</aixm:deliveryPoint>
            </aixm:PostalAddress>
          </aixm:address>
        </aixm:ContactInformation>
      </aixm:contact>
      <aixm:availability>
        <aixm:AirportHeliportAvailability gml:id="uuid.136aa0cf-db24-4c67-bd5a-bd020f843f12">
          <aixm:timeInterval>
            <aixm:Timesheet gml:id="uuid.6abcd956-fb5e-42b7-a9ce-374696018935">
              <aixm:timeReference>UTC</aixm:timeReference>
              <aixm:startDate>01-01</aixm:startDate>
              <aixm:endDate>31-12</aixm:endDate>
              <aixm:day>WORK_DAY</aixm:day>
              <aixm:dayTil>WORK_DAY</aixm:dayTil>
              <aixm:startTime>07:30</aixm:startTime>
              <aixm:endTime>15:00</aixm:endTime>
              <aixm:daylightSavingAdjust>NO</aixm:daylightSavingAdjust>
              <aixm:excluded>NO</aixm:excluded>
            </aixm:Timesheet>
          </aixm:timeInterval>
          <aixm:operationalStatus>NORMAL</aixm:operationalStatus>
          <aixm:usage>
            <aixm:AirportHeliportUsage gml:id="uuid.9673f98c-3f79-4ffe-9186-1ad4415d684a">
              <aixm:type>PERMIT</aixm:type>
              <aixm:selection>
                <aixm:ConditionCombination gml:id="uuid.845f1bcd-3957-4c40-a55b-ba1a70f394f7">
                  <aixm:logicalOperator>OR</aixm:logicalOperator>
                  <aixm:flight>
                    <aixm:FlightCharacteristic gml:id="uuid.ccd59269-9086-4a22-a49c-9a0c3a42aa0b">
                      <aixm:rule>VFR</aixm:rule>
                      <aixm:military>CIVIL</aixm:military>
                      <aixm:origin>NTL</aixm:origin>
                      <aixm:purpose>NON_SCHEDULED</aixm:purpose>
                    </aixm:FlightCharacteristic>
                  </aixm:flight>
                  <aixm:flight>
                    <aixm:FlightCharacteristic gml:id="uuid.a4199076-3723-4227-9fee-3f5a7357d0f1">
                      <aixm:rule>VFR</aixm:rule>
                      <aixm:military>CIVIL</aixm:military>
                      <aixm:origin>NTL</aixm:origin>
                      <aixm:purpose>PRIVATE</aixm:purpose>
                    </aixm:FlightCharacteristic>
                  </aixm:flight>
                </aixm:ConditionCombination>
              </aixm:selection>
            </aixm:AirportHeliportUsage>
          </aixm:usage>
        </aixm:AirportHeliportAvailability>
      </aixm:availability>
      <aixm:annotation>
        <aixm:Note gml:id="uuid.992f3d73-0d8e-443b-b3ca-24e741e5f31d">
          <aixm:purpose>OTHER:AIXM_4_5_MAPPING</aixm:purpose>
          <aixm:translatedNote>
            <aixm:LinguisticNote gml:id="uuid.6838080a-513d-47ba-8dbb-e7728ebeafb7">
              <aixm:note>CRC:454145N, 0253202E, 1744, 126, A6065917</aixm:note>
            </aixm:LinguisticNote>
          </aixm:translatedNote>
        </aixm:Note>
      </aixm:annotation>
      <aixm:annotation>
        <aixm:Note gml:id="uuid.89aeac3c-16fc-4173-9e8b-92fb8f207aae">
          <aixm:purpose>OTHER:AIXM_4_5_MAPPING</aixm:purpose>
          <aixm:translatedNote>
            <aixm:LinguisticNote gml:id="uuid.6f4ded9e-86ab-448d-88d3-7551cd5f8641">
              <aixm:note>Site Description:4 NM West Brasov / 1.5 NM North-East Ghimbav</aixm:note>
            </aixm:LinguisticNote>
          </aixm:translatedNote>
        </aixm:Note>
      </aixm:annotation>
    </aixm:AirportHeliportTimeSlice>
  </aixm:timeSlice>
</aixm:AirportHeliport> 
  </message:hasMember>

</message:AIXMBasicMessage>

