<?xml version="1.0" encoding="UTF-8"?>
<message:AIXMBasicMessage xmlns:message="http://www.aixm.aero/schema/5.1.1/message"
                          xmlns:gts="http://www.isotc211.org/2005/gts" xmlns:gco="http://www.isotc211.org/2005/gco"
                          xmlns:xsd="http://www.w3.org/2001/XMLSchema" xmlns:gml="http://www.opengis.net/gml/3.2"
                          xmlns:gss="http://www.isotc211.org/2005/gss" xmlns:aixm="http://www.aixm.aero/schema/5.1.1"
                          xmlns:gsr="http://www.isotc211.org/2005/gsr" xmlns:gmd="http://www.isotc211.org/2005/gmd"
                           xmlns:xlink="http://www.w3.org/1999/xlink"
                          xmlns:xsi="http://www.w3.org/2001/XMLSchema-instance"
                          xsi:schemaLocation="http://www.aixm.aero/schema/5.1.1/message http://www.aixm.aero/schema/5.1.1/message/AIXM_BasicMessage.xsd
                          http://www.aixm.aero/schema/5.1/event http://www.aixm.aero/schema/5.1.1/event/version_5.1-e/Event_Features.xsd"
                          gml:id="M00001">
    <message:hasMember xmlns:xsi="http://www.w3.org/2001/XMLSchema-instance">
        <aixm:PilotControlledLighting gml:id="uuid.833f2353-52f1-4826-80f8-d01b6d8297bf">
            <gml:identifier codeSpace="urn:uuid:">833f2353-52f1-4826-80f8-d01b6d8297bf</gml:identifier>
            <gml:boundedBy xsi:nil="true"/>
            <aixm:timeSlice>
                <aixm:PilotControlledLightingTimeSlice gml:id="uuid.353a6e9d-f87b-4470-8b24-269cd08477c2">
                    <gml:validTime>
                        <gml:TimePeriod gml:id="uuid.feb11a9e-2593-4859-b6b8-0f849c0d4b97">
                            <gml:beginPosition>2023-05-18T00:00:00Z</gml:beginPosition>
                            <gml:endPosition indeterminatePosition="unknown"/>
                        </gml:TimePeriod>
                    </gml:validTime>
                    <aixm:interpretation>BASELINE</aixm:interpretation>
                    <aixm:sequenceNumber>5</aixm:sequenceNumber>
                    <aixm:correctionNumber>0</aixm:correctionNumber>
                    <aixm:featureLifetime>
                        <gml:TimePeriod gml:id="uuid.0582293c-c112-4661-a766-49ec3807c801">
                            <gml:beginPosition>2021-10-07T00:00:00Z</gml:beginPosition>
                            <gml:endPosition indeterminatePosition="unknown"/>
                        </gml:TimePeriod>
                    </aixm:featureLifetime>
                    <aixm:controlledLightIntensity>
                        <aixm:LightActivation gml:id="uuid.030b2521-abcd-effe-cdcd-9e8bdcfd000">
                            <aixm:clicks>3</aixm:clicks>
                            <aixm:intensityLevel>LIH</aixm:intensityLevel>
                            <aixm:activation>OFF</aixm:activation>
                            <aixm:annotation>
                                <aixm:Note gml:id="uuid.19dfc7d4-abd0-4776-989e-1951e1bcfd20">
                                    <!-- WARNING It is prohibited that LightActivation has annotation.Note.propertyName value other-than-one-of ('clicks', 'intensityLevel', 'activation')  -->
                                    <aixm:propertyName>invalidPropertyName</aixm:propertyName>
                                </aixm:Note>
                            </aixm:annotation>
                        </aixm:LightActivation>
                    </aixm:controlledLightIntensity>
                </aixm:PilotControlledLightingTimeSlice>
            </aixm:timeSlice>
        </aixm:PilotControlledLighting>
    </message:hasMember>
</message:AIXMBasicMessage>
