<?xml version="1.0" encoding="UTF-8"?>
<message:AIXMBasicMessage xmlns:message="http://www.aixm.aero/schema/5.1.1/message"
                          xmlns:gts="http://www.isotc211.org/2005/gts" xmlns:gco="http://www.isotc211.org/2005/gco"
                          xmlns:xsd="http://www.w3.org/2001/XMLSchema" xmlns:gml="http://www.opengis.net/gml/3.2"
                          xmlns:gss="http://www.isotc211.org/2005/gss" xmlns:aixm="http://www.aixm.aero/schema/5.1.1"
                          xmlns:gsr="http://www.isotc211.org/2005/gsr" xmlns:gmd="http://www.isotc211.org/2005/gmd"
                           xmlns:xlink="http://www.w3.org/1999/xlink"
                          xmlns:xsi="http://www.w3.org/2001/XMLSchema-instance"
                          xsi:schemaLocation="http://www.aixm.aero/schema/5.1.1/message http://www.aixm.aero/schema/5.1.1/message/AIXM_BasicMessage.xsd"
                          gml:id="M00001">
    <message:hasMember xmlns:xsi="http://www.w3.org/2001/XMLSchema-instance">
        <aixm:MissedApproachLeg gml:id="uuid.f9b2ef26-1ccb-44e8-b5ab-572a2998626b">
            <gml:identifier codeSpace="urn:uuid:">f9b2ef26-1ccb-44e8-b5ab-572a2998626b</gml:identifier>
            <aixm:timeSlice>
                <aixm:MissedApproachLegTimeSlice gml:id="ID_1A4A9F_01">
                    <gml:validTime>
                        <gml:TimePeriod gml:id="ID_1A4A9F_02">
                            <gml:beginPosition>2020-12-03T00:00:00Z</gml:beginPosition>
                            <gml:endPosition indeterminatePosition="unknown"/>
                        </gml:TimePeriod>
                    </gml:validTime>
                    <aixm:interpretation>BASELINE</aixm:interpretation>
                    <aixm:sequenceNumber>1</aixm:sequenceNumber>
                    <aixm:endConditionDesignator>ALTITUDE</aixm:endConditionDesignator>
                    <aixm:legPath>ARC</aixm:legPath>
                    <aixm:legTypeARINC>AF</aixm:legTypeARINC>
                    <aixm:course>1</aixm:course>
                    <aixm:courseType>HDG</aixm:courseType>
                    <aixm:courseDirection>FROM</aixm:courseDirection>
                    <aixm:turnDirection>EITHER</aixm:turnDirection>
                    <aixm:speedLimit>100</aixm:speedLimit>
                    <aixm:speedReference>GS</aixm:speedReference>
                    <aixm:speedInterpretation>ABOVE_LOWER</aixm:speedInterpretation>
                    <aixm:bankAngle>10</aixm:bankAngle>
                    <aixm:length>10</aixm:length>
                    <aixm:duration>100</aixm:duration>
                    <aixm:procedureTurnRequired>YES</aixm:procedureTurnRequired>
                    <aixm:upperLimitAltitude uom="FL">660</aixm:upperLimitAltitude>
                    <aixm:upperLimitReference>STD</aixm:upperLimitReference>
                    <aixm:lowerLimitAltitude uom="FL">110</aixm:lowerLimitAltitude>
                    <aixm:lowerLimitReference>STD</aixm:lowerLimitReference>
                    <aixm:altitudeInterpretation>ABOVE_LOWER</aixm:altitudeInterpretation>
                    <!-- If uom='FL' the value for InitialLeg.altitudeOverrideATC should be expressed with 1,2 or 3 digits -->
                    <aixm:altitudeOverrideATC uom="FL">200</aixm:altitudeOverrideATC>
                    <aixm:altitudeOverrideReference>STD</aixm:altitudeOverrideReference>
                    <aixm:verticalAngle>40</aixm:verticalAngle>
                    <aixm:startPoint>
                        <aixm:TerminalSegmentPoint gml:id="ID_1A8CE1_03">
                            <aixm:pointChoice_fixDesignatedPoint xlink:href="urn:uuid:f881efdf-d738-4c87-a49f-cba15827db19"/>
                        </aixm:TerminalSegmentPoint>
                    </aixm:startPoint>
                    <aixm:endPoint>
                        <aixm:TerminalSegmentPoint gml:id="ID_1A8CE1_04">
                            <aixm:pointChoice_fixDesignatedPoint xlink:href="urn:uuid:29cc2f39-78c3-4ca1-8f6a-7236a0b25f7c"/>
                        </aixm:TerminalSegmentPoint>
                    </aixm:endPoint>
                    <aixm:trajectory>
                        <aixm:Curve>
                            <gml:segments>
                                <gml:GeodesicString>
                                    <gml:posList>25.652485 48.532658 26.356898 49.5874621 26.846985 49.67458214 25.652485 48.532658</gml:posList>
                                </gml:GeodesicString>
                            </gml:segments>
                        </aixm:Curve>
                    </aixm:trajectory>
                    <aixm:arcCentre>
                        <aixm:TerminalSegmentPoint  gml:id="ID_1A8CE1_15">
                            <aixm:pointChoice_fixDesignatedPoint xlink:href="urn:uuid:f881efdf-d738-4c87-a49f-cba15827db19"/>
                        </aixm:TerminalSegmentPoint>
                    </aixm:arcCentre>
                    <aixm:angle/>
                    <aixm:distance/>
                    <aixm:aircraftCategory>
                        <aixm:AircraftCharacteristic gml:id="uuid.030b2521-abcd-effe-cdcd-9e8bdcfd000"/>
                    </aixm:aircraftCategory>
                    <aixm:holding>
                        <aixm:HoldingUse gml:id="uuid.030b2521-abcd-effe-cdcd-9e8bdcfd001"/>
                    </aixm:holding>
                    <aixm:designSurface>
                        <aixm:ObstacleAssessmentArea gml:id="uuid.030b2521-abcd-effe-cdcd-9e8bdcfd002"/>
                    </aixm:designSurface>
                    <aixm:annotation>
                        <aixm:Note gml:id="uuid.19dfc7d4-abd0-4776-989e-1951e1bcfd20">
                            <!-- WARNING It is prohibited that MissedApproachLegTimeSlice has annotation.Note.propertyName value other-than-one-of ('endConditionDesignator', 'legPath', 'legTypeARINC', 'course', 'courseType', 'courseDirection', 'turnDirection', 'speedLimit', 'speedReference', 'speedInterpretation', 'bankAngle', 'length', 'duration', 'procedureTurnRequired', 'upperLimitAltitude', 'upperLimitReference', 'lowerLimitAltitude', 'lowerLimitReference', 'altitudeInterpretation', 'altitudeOverrideATC', 'altitudeOverrideReference', 'verticalAngle', 'startPoint', 'endPoint', 'trajectory', 'arcCentre', 'angle', 'distance', 'aircraftCategory', 'holding', 'designSurface', 'approach', 'type', 'thresholdAfterMAPT', 'heightMAPT', 'requiredNavigationPerformance', 'condition')  -->
                            <aixm:propertyName>invalidPropertyName</aixm:propertyName>
                        </aixm:Note>
                    </aixm:annotation>
                    <aixm:approach/>
                    <aixm:type>ALTERNATE</aixm:type>
                    <aixm:thresholdAfterMAPT>YES</aixm:thresholdAfterMAPT>
                    <aixm:heightMAPT>100</aixm:heightMAPT>
                    <aixm:requiredNavigationPerformance>1</aixm:requiredNavigationPerformance>
                    <aixm:condition>
                        <aixm:ApproachCondition gml:id="uuid.030b2521-abcd-effe-cdcd-9e8bdcfd003"/>
                    </aixm:condition>
                </aixm:MissedApproachLegTimeSlice>
            </aixm:timeSlice>
        </aixm:MissedApproachLeg>
    </message:hasMember>
    <message:hasMember>
        <aixm:DesignatedPoint gml:id="uuid.f881efdf-d738-4c87-a49f-cba15827db19">
            <gml:identifier codeSpace="urn:uuid:">f881efdf-d738-4c87-a49f-cba15827db19</gml:identifier>
            <aixm:timeSlice>
                <aixm:DesignatedPointTimeSlice gml:id="ID_1A8CE1_05">
                    <gml:validTime>
                        <gml:TimePeriod gml:id="ID_1A8CE1_06">
                            <gml:beginPosition>2020-12-03T00:00:00Z</gml:beginPosition>
                            <gml:endPosition indeterminatePosition="unknown"/>
                        </gml:TimePeriod>
                    </gml:validTime>
                    <aixm:interpretation>BASELINE</aixm:interpretation>
                    <aixm:sequenceNumber>1</aixm:sequenceNumber>
                    <aixm:designator>DONLO</aixm:designator>
                    <aixm:type>ICAO</aixm:type>
                    <aixm:location>
                        <aixm:Point gml:id="ID_1A8CE1_07" srsName="urn:ogc:def:crs:EPSG::4326">
                            <!-- Coordinates should be expressed with 5 or more decimals -->
                            <gml:pos>21.123456 41.123456</gml:pos>
                        </aixm:Point>
                    </aixm:location>
                </aixm:DesignatedPointTimeSlice>
            </aixm:timeSlice>
        </aixm:DesignatedPoint>
    </message:hasMember>
    <message:hasMember>
        <aixm:DesignatedPoint gml:id="uuid.29cc2f39-78c3-4ca1-8f6a-7236a0b25f7c">
            <gml:identifier codeSpace="urn:uuid:">29cc2f39-78c3-4ca1-8f6a-7236a0b25f7c</gml:identifier>
            <aixm:timeSlice>
                <aixm:DesignatedPointTimeSlice gml:id="ID_1A8CE1_08">
                    <gml:validTime>
                        <gml:TimePeriod gml:id="ID_1A8CE1_09">
                            <gml:beginPosition>2020-12-03T00:00:00Z</gml:beginPosition>
                            <gml:endPosition indeterminatePosition="unknown"/>
                        </gml:TimePeriod>
                    </gml:validTime>
                    <aixm:interpretation>BASELINE</aixm:interpretation>
                    <aixm:sequenceNumber>1</aixm:sequenceNumber>
                    <aixm:designator>DONON</aixm:designator>
                    <aixm:type>ICAO</aixm:type>
                    <aixm:location>
                        <aixm:Point gml:id="ID_1A8CE1_10" srsName="urn:ogc:def:crs:EPSG::4326">
                            <gml:pos>11.123456 11.123456</gml:pos>
                        </aixm:Point>
                    </aixm:location>
                </aixm:DesignatedPointTimeSlice>
            </aixm:timeSlice>
        </aixm:DesignatedPoint>
    </message:hasMember>
</message:AIXMBasicMessage>
