<?xml version="1.0" encoding="UTF-8"?>
<message:AIXMBasicMessage xmlns:message="http://www.aixm.aero/schema/5.1.1/message"
                          xmlns:gts="http://www.isotc211.org/2005/gts" xmlns:gco="http://www.isotc211.org/2005/gco"
                          xmlns:xsd="http://www.w3.org/2001/XMLSchema" xmlns:gml="http://www.opengis.net/gml/3.2"
                          xmlns:gss="http://www.isotc211.org/2005/gss" xmlns:aixm="http://www.aixm.aero/schema/5.1.1"
                          xmlns:gsr="http://www.isotc211.org/2005/gsr" xmlns:gmd="http://www.isotc211.org/2005/gmd"
                          xmlns:xlink="http://www.w3.org/1999/xlink"
                          xmlns:xsi="http://www.w3.org/2001/XMLSchema-instance"
                          xmlns:adr="http://www.aixm.aero/schema/5.1.1/extensions/EUR/ADR"
                          xsi:schemaLocation="http://www.aixm.aero/schema/5.1.1/message http://www.aixm.aero/schema/5.1.1/message/AIXM_BasicMessage.xsd                          "
                          gml:id="M00001">
    <message:hasMember>
        <aixm:Navaid gml:id="uuid.8e8e4475-cb2d-4c0f-b29d-fc4eb9b044bf">
            <gml:identifier codeSpace="urn:uuid:">8e8e4475-cb2d-4c0f-b29d-fc4eb9b044bf</gml:identifier>
            <gml:boundedBy xsi:nil="true"/>
            <aixm:timeSlice>
                <aixm:NavaidTimeSlice gml:id="uuid.9039efaf-ea3c-4f7b-a771-fc04b0afbefe">
                    <gml:validTime>
                        <gml:TimePeriod gml:id="uuid.a428c923-c74d-4bf6-9c19-5a6598619b59">
                            <gml:beginPosition>2013-02-15T00:00:00Z</gml:beginPosition>
                            <gml:endPosition indeterminatePosition="unknown"/>
                        </gml:TimePeriod>
                    </gml:validTime>
                    <aixm:interpretation>BASELINE</aixm:interpretation>
                    <aixm:sequenceNumber>1</aixm:sequenceNumber>
                    <aixm:correctionNumber>0</aixm:correctionNumber>
                    <aixm:featureLifetime>
                        <gml:TimePeriod gml:id="uuid.23b98416-84f2-4c98-b00f-1ebbf1371917">
                            <gml:beginPosition>2012-06-17T00:00:00Z</gml:beginPosition>
                            <gml:endPosition indeterminatePosition="unknown"/>
                        </gml:TimePeriod>
                    </aixm:featureLifetime>
                    <aixm:type>NDB_MKR</aixm:type>
                    <aixm:designator>C</aixm:designator>
                    <aixm:name>KYIV/ANTONOV</aixm:name>
                    <aixm:navaidEquipment>
                        <aixm:NavaidComponent gml:id="uuid.0ed67a8a-577b-4bae-a07a-f9c9a47db2f0">
                            <aixm:collocationGroup>1</aixm:collocationGroup>
                            <aixm:markerPosition>MIDDLE</aixm:markerPosition>
                            <aixm:providesNavigableLocation>NO</aixm:providesNavigableLocation>
                            <aixm:theNavaidEquipment xlink:type="simple"
                                                     xlink:href="#uuid.b76bad8c-abc9-471e-8088-bd4fdc3428dc"/>
                        </aixm:NavaidComponent>
                    </aixm:navaidEquipment>
                    <aixm:navaidEquipment>
                        <aixm:NavaidComponent gml:id="uuid.67e87a75-5c57-44dd-9067-526c8afb5e58">
                            <aixm:collocationGroup>1</aixm:collocationGroup>
                            <aixm:providesNavigableLocation>YES</aixm:providesNavigableLocation>
                            <!-- ERROR: Found 'NDB_MKR' Navaid composed of incorrect equipment (SDF) -->
                            <aixm:theNavaidEquipment xlink:type="simple"
                                                     xlink:href="#uuid.57568894-77ae-4281-a56c-6f8a6b1389d0"/>
                        </aixm:NavaidComponent>
                    </aixm:navaidEquipment>
                    <aixm:location>
                        <aixm:ElevatedPoint xmlns="http://www.aixm.aero/schema/5.1.1/message"
                                            xmlns:adr="http://www.aixm.aero/schema/5.1.1/extensions/EUR/ADR"
                                            xmlns:gmd="http://www.isotc211.org/2005/gmd"
                                            xmlns:gco="http://www.isotc211.org/2005/gco"
                                            xmlns:qualityreport="http://www.aixm.aero/schema/5.1.1/extensions/qualityreport"
                                            xmlns:xlink="http://www.w3.org/1999/xlink"
                                            xmlns:gml="http://www.opengis.net/gml/3.2"
                                            xmlns:ead="http://www.aixm.aero/schema/5.1.1/extensions/EUR/EAD/Slot"
                                            xmlns:gts="http://www.isotc211.org/2005/gts"
                                            xmlns:aixm="http://www.aixm.aero/schema/5.1.1"
                                            srsName="urn:ogc:def:crs:EPSG::4326"
                                            gml:id="uuid.68bae1b2-d423-4cf3-95b3-839f265fc794">
                            <gml:pos>50.62583 30.17472</gml:pos>
                            <aixm:annotation>
                                <aixm:Note gml:id="uuid.17fd1d1b-626e-4e20-a80b-3b0e6f3f6ae0">
                                    <aixm:purpose>OTHER:AIXM_4_5_MAPPING</aixm:purpose>
                                    <aixm:translatedNote>
                                        <aixm:LinguisticNote gml:id="uuid.0353e55b-14fd-4346-97a5-91d52a95db9e">
                                            <aixm:note>CRC:503733N, 0301029E, , , 799F9B90</aixm:note>
                                        </aixm:LinguisticNote>
                                    </aixm:translatedNote>
                                </aixm:Note>
                            </aixm:annotation>
                        </aixm:ElevatedPoint>
                    </aixm:location>
                    <aixm:servedAirport xlink:type="simple" xlink:href="urn:uuid:909b3b87-c3d3-41b9-844e-8ac4b58a69b2"/>
                </aixm:NavaidTimeSlice>
            </aixm:timeSlice>
        </aixm:Navaid>
    </message:hasMember>

    <message:hasMember xmlns:xsi="http://www.w3.org/2001/XMLSchema-instance">
        <aixm:SDF gml:id="uuid.57568894-77ae-4281-a56c-6f8a6b1389d0">
            <gml:identifier codeSpace="urn:uuid:">57568894-77ae-4281-a56c-6f8a6b1389d0</gml:identifier>
            <gml:boundedBy xsi:nil="true"/>
            <aixm:timeSlice>
                <aixm:SDFTimeSlice gml:id="uuid.203ae95e-3d2a-4e44-ba6f-1856457f61f1">
                    <gml:validTime>
                        <gml:TimePeriod gml:id="uuid.601046f4-f370-40b7-b87f-1acb5353735d">
                            <gml:beginPosition>2015-12-10T00:00:00Z</gml:beginPosition>
                            <gml:endPosition indeterminatePosition="unknown"/>
                        </gml:TimePeriod>
                    </gml:validTime>
                    <aixm:interpretation>BASELINE</aixm:interpretation>
                    <aixm:sequenceNumber>1</aixm:sequenceNumber>
                    <aixm:correctionNumber>0</aixm:correctionNumber>
                    <aixm:featureLifetime>
                        <gml:TimePeriod gml:id="uuid.7cf5d0eb-fb1d-49f3-a8f2-36bbf2dfccdc">
                            <gml:beginPosition>2003-01-30T00:00:00Z</gml:beginPosition>
                            <gml:endPosition indeterminatePosition="unknown"/>
                        </gml:TimePeriod>
                    </aixm:featureLifetime>
                    <aixm:designator>C</aixm:designator>
                    <aixm:name>KYIV/ANTONOV</aixm:name>
                    <aixm:magneticVariation>7</aixm:magneticVariation>
                    <aixm:dateMagneticVariation>2014</aixm:dateMagneticVariation>
                    <aixm:location>
                        <aixm:ElevatedPoint xmlns="http://www.aixm.aero/schema/5.1.1/message"
                                            xmlns:adr="http://www.aixm.aero/schema/5.1.1/extensions/EUR/ADR"
                                            xmlns:gmd="http://www.isotc211.org/2005/gmd"
                                            xmlns:gco="http://www.isotc211.org/2005/gco"
                                            xmlns:qualityreport="http://www.aixm.aero/schema/5.1.1/extensions/qualityreport"
                                            xmlns:xlink="http://www.w3.org/1999/xlink"
                                            xmlns:gml="http://www.opengis.net/gml/3.2"
                                            xmlns:ead="http://www.aixm.aero/schema/5.1.1/extensions/EUR/EAD/Slot"
                                            xmlns:gts="http://www.isotc211.org/2005/gts"
                                            xmlns:aixm="http://www.aixm.aero/schema/5.1.1"
                                            srsName="urn:ogc:def:crs:EPSG::4326"
                                            gml:id="uuid.ce3ab25d-3f90-4c00-a42d-e0f44b4557d7">
                            <gml:pos>50.62583 30.17472</gml:pos>
                            <aixm:annotation>
                                <aixm:Note gml:id="uuid.ac5f6838-fe7c-4490-adb5-fc3cd063c205">
                                    <aixm:purpose>OTHER:AIXM_4_5_MAPPING</aixm:purpose>
                                    <aixm:translatedNote>
                                        <aixm:LinguisticNote gml:id="uuid.1e17197d-a548-4947-8aa7-a31da224009e">
                                            <aixm:note>CRC:503733N, 0301029E, , , 799F9B90</aixm:note>
                                        </aixm:LinguisticNote>
                                    </aixm:translatedNote>
                                </aixm:Note>
                            </aixm:annotation>
                        </aixm:ElevatedPoint>
                    </aixm:location>
                    <aixm:authority>
                        <aixm:AuthorityForNavaidEquipment gml:id="uuid.2db1270e-d591-42f1-8dcc-28e5ba56e676">
                            <aixm:theOrganisationAuthority xlink:type="simple"
                                                           xlink:href="urn:uuid:09424934-89a6-0ae9-e053-0b751dc2b779"/>
                        </aixm:AuthorityForNavaidEquipment>
                    </aixm:authority>
                    <aixm:availability>
                        <aixm:NavaidOperationalStatus gml:id="uuid.c982e9c8-7649-4651-a043-61dfdfecce44">
                            <aixm:timeInterval>
                                <aixm:Timesheet gml:id="uuid.90395c95-6a5d-4b62-b7e5-338b68d43968">
                                    <aixm:timeReference>UTC</aixm:timeReference>
                                    <aixm:startDate>01-01</aixm:startDate>
                                    <aixm:endDate>31-12</aixm:endDate>
                                    <aixm:day>WORK_DAY</aixm:day>
                                    <aixm:startTime>07:30</aixm:startTime>
                                    <aixm:endTime>15:00</aixm:endTime>
                                    <aixm:daylightSavingAdjust>YES</aixm:daylightSavingAdjust>
                                    <aixm:excluded>NO</aixm:excluded>
                                </aixm:Timesheet>
                            </aixm:timeInterval>
                        </aixm:NavaidOperationalStatus>
                    </aixm:availability>
                    <aixm:frequency uom="KHZ">257</aixm:frequency>
                </aixm:SDFTimeSlice>
            </aixm:timeSlice>
        </aixm:SDF>
    </message:hasMember>

</message:AIXMBasicMessage>
